{
  "fr": {
    "title": "Bienvenue sur le portfolio de Amira Haouet",
    "intro": "Étudiante en informatique passionnée par le développement logiciel et l'intelligence artificielle.",
    "objective": "Objectif Professionnel",
    "objective_content": "Actuellement en alternance chez Holy-Dis, je développe mes compétences en développement full stack et en intelligence artificielle.",
    "skills": "Compétences",
    "experience": "Expériences",
    "education": "Formation",
    "contact": "Contact",
    "video": "Vidéo de présentation",
    "footer": "Voir en ligne :"
  },
  "en": {
    "title": "Welcome to Amira Haouet’s portfolio",
    "intro": "Computer science student passionate about software development and artificial intelligence.",
    "objective": "Professional Objective",
    "objective_content": "Currently doing a work-study at Holy-Dis, developing full-stack and AI skills.",
    "skills": "Skills",
    "experience": "Experience",
    "education": "Education",
    "contact": "Contact",
    "video": "Presentation Video",
    "footer": "Online version:"
  },
  "ar": {
    "title": "مرحبًا بكم في ملف أميرة حاوت",
    "intro": "طالبة في علوم الحاسوب شغوفة بتطوير البرمجيات والذكاء الاصطناعي.",
    "objective": "الهدف المهني",
    "objective_content": "أقوم حاليًا بتدريب مهني في شركة Holy-Dis حيث أطور مهاراتي في تطوير البرمجيات والذكاء الاصطناعي.",
    "skills": "المهارات",
    "experience": "الخبرات",
    "education": "التعليم",
    "contact": "تواصل",
    "video": "فيديو تعريفي",
    "footer": "رابط مباشر:"
  }
}
